phlame/__init__.py
phlame/classify.py
phlame/cmt2tree.py
phlame/countsCMT.py
phlame/helper_functions.py
phlame/makedb.py
phlame/plot.py
phlame/ss_caller_module.py
phlame/tree.py
phlame-1.1.0.data/scripts/phlame
phlame-1.1.0.dist-info/METADATA
phlame-1.1.0.dist-info/WHEEL
phlame-1.1.0.dist-info/top_level.txt
phlame-1.1.0.dist-info/RECORD
