Metadata-Version: 2.2
Name: phlame
Version: 1.1.0
Summary: Novelty-aware intraspecies profiling of metagenome samples
Home-page: https://github.com/quevan/phlame
Author: Evan Qu
Author-email: equ@mit.edu
License: MIT
Requires-Python: >=3.8, <3.13
Requires-Dist: numpy
Requires-Dist: pandas
Requires-Dist: matplotlib
Requires-Dist: biopython
Requires-Dist: ete3
Requires-Dist: statsmodels
Requires-Dist: pytest
Dynamic: author
Dynamic: author-email
Dynamic: home-page
Dynamic: license
Dynamic: requires-dist
Dynamic: requires-python
Dynamic: summary
